{
  "best_model_name": "ExtraTreesRegressor",
  "best_model_key": "extra_trees",
  "artifact_path": "models/real_estate_price_pipeline.joblib",
  "data_path": "data/nekretnine_raw.csv",
  "feature_columns": [
    "area_m2",
    "rooms",
    "floor",
    "total_floors",
    "is_last_floor",
    "year_built",
    "building_age",
    "is_lux",
    "is_penthouse",
    "is_duplex",
    "city",
    "region",
    "heating_type",
    "parking"
  ],
  "metrics": [
    {
      "model": "ExtraTreesRegressor",
      "mae": 31150.92293784356,
      "rmse": 58656.3815946122,
      "r2": 0.8460077236985877,
      "rank_by_mae": 1
    },
    {
      "model": "RandomForestRegressor",
      "mae": 32626.419365094265,
      "rmse": 60717.67270131121,
      "r2": 0.8349944184857805,
      "rank_by_mae": 2
    },
    {
      "model": "HistGradientBoostingRegressor",
      "mae": 36806.60897004431,
      "rmse": 62601.498597223115,
      "r2": 0.8245966591366198,
      "rank_by_mae": 3
    },
    {
      "model": "GradientBoostingRegressor",
      "mae": 42999.73998751152,
      "rmse": 68975.4905771325,
      "r2": 0.7870596333650541,
      "rank_by_mae": 4
    },
    {
      "model": "RidgeRegression",
      "mae": 51331.923295629305,
      "rmse": 81380.91996762659,
      "r2": 0.7035758443413422,
      "rank_by_mae": 5
    },
    {
      "model": "LinearRegression",
      "mae": 51659.08930884977,
      "rmse": 81785.46766249514,
      "r2": 0.7006214474949314,
      "rank_by_mae": 6
    },
    {
      "model": "Baseline - DummyRegressor median",
      "mae": 97351.25013401233,
      "rmse": 156895.49882234403,
      "r2": -0.10176600994127072,
      "rank_by_mae": 7
    }
  ],
  "raw_rows": 20584,
  "cleaned_rows": 18651,
  "train_rows": 14920,
  "test_rows": 3731,
  "test_size": 0.2,
  "random_state": 42,
  "ui_options": {
    "cities": [
      "Aleksinac",
      "Aranđelovac",
      "Bajina Bašta",
      "Banja Koviljača",
      "Banja Luka",
      "Bar",
      "Bačka Palanka",
      "Bački Jarak",
      "Bela Crkva",
      "Beograd",
      "Beočin",
      "Bečej",
      "Bečići",
      "Bor",
      "Brzeće",
      "Bubanj",
      "Budva",
      "Despotovac",
      "Divčibare",
      "Dobrota",
      "Donja Lastva",
      "Donji Orahovac",
      "Futog",
      "GRČKA – SOLUN – CENTAR AGIOU DIMITRIOU 76 – 38 m² – 158.000 €",
      "Glifada",
      "Herceg Novi",
      "Inđija",
      "Irig",
      "Ivanjica",
      "Jagodina",
      "Jahorina",
      "Kikinda",
      "Kopaonik",
      "Kosjerić (varoš)",
      "Kotor",
      "Kovin",
      "Kragujevac",
      "Kraljevo",
      "Kruševac",
      "Kula",
      "Kumbor",
      "Kuršumlija",
      "Lastva Grbaljska",
      "Leskovac",
      "Ljubovija",
      "Loznica",
      "Luštica",
      "Mali Iđoš",
      "Mladenovac",
      "Mladenovac (selo)",
      "Mrčevac",
      "Muo",
      "Nepoznato",
      "Niš",
      "Nova Varoš",
      "Novi Bečej",
      "Novi Sad",
      "Novi Vinodolski",
      "Obrenovac",
      "Pančevo",
      "Paraćin",
      "Petrovac na Mlavi",
      "Petrovac na Moru",
      "Petrovaradin",
      "Podgorica",
      "Popinci",
      "Požarevac",
      "Prijepolje",
      "Prokuplje",
      "Pržno",
      "Radovići",
      "Raška",
      "Ripanj",
      "Ruma",
      "Smederevo",
      "Smederevska Palanka",
      "Sokobanja",
      "Sombor",
      "Sopot",
      "Srbobran",
      "Sremska Kamenica",
      "Sremska Mitrovica",
      "Sremski Karlovci",
      "Stara Pazova",
      "Stari Bar",
      "Subotica",
      "Sutvara",
      "Sveti Stefan",
      "Tara (planina)",
      "Temerin",
      "Tivat",
      "Trebinje",
      "Trstenik",
      "Umka",
      "Užice",
      "Valjevo",
      "Veliko Gradište",
      "Veternik",
      "Vranje",
      "Vrbas",
      "Vrdnik",
      "Vrnjačka Banja",
      "Vrčin",
      "Vršac",
      "Zaječar",
      "Zlatibor",
      "Zrenjanin",
      "Ćuprija",
      "Čajetina",
      "Čačak",
      "Čelarevo",
      "Šabac",
      "Šimanovci"
    ],
    "regions": [
      "18 jul",
      "29. Novembra",
      "Adamovićevo naselje",
      "Adice",
      "Aerodrom",
      "Aksentija Maksimovića",
      "Albanske spomenice",
      "Aleksandra Nenadovica",
      "Alekse Celebonovica",
      "Alibegovac",
      "Altina",
      "Andrije Jevremovića",
      "Andrićev venac",
      "Antifašističke borbe",
      "Antuna Urbana",
      "Apartmani TRESKA",
      "Apelovac",
      "Arčibalda Rajsa",
      "Autokomanda",
      "Avala",
      "Avalska",
      "Avenija",
      "Avijatičarsko naselje",
      "BULEVAR DESPOTA STEFANA",
      "Babicki Odred",
      "Bagremar",
      "Bajlonijeva pijaca",
      "Banatić",
      "Banija",
      "Banjica",
      "Banjski šor",
      "Banovo brdo",
      "Barajevo",
      "Batajnica",
      "Bela reka",
      "Bele reke",
      "Bele vode",
      "Belog narcisa",
      "Beograd na vodi",
      "Beogradski kej",
      "Beograđanka ( centar )",
      "Betanija",
      "Beverli hils",
      "Beška",
      "Bežanija",
      "Bežanijska kosa I",
      "Bežanijska kosa II",
      "Bežanijska kosa III",
      "Bistrica",
      "Blok 8",
      "Blok 9",
      "Blok vila",
      "Bogoslovija",
      "Bokokotorska",
      "Boleč",
      "Boljevci",
      "Bore Vasiljevića",
      "Borjak",
      "Borča I",
      "Borča II",
      "Borča III",
      "Bostani",
      "Botanička bašta",
      "Božidarčeva",
      "Branislava Bukurova",
      "Branka Krsmanovica",
      "Branka Krsmanovića",
      "Branka Radičevića",
      "Branko Bjegović",
      "Braće Jerković",
      "Braće Jovanovića",
      "Braće Miladinov",
      "Braće Rabrenović",
      "Breza",
      "Bronks",
      "Brunova",
      "Bubanj",
      "Bucarska 17",
      "Bulbuder",
      "Bulevar",
      "Bulevar Arsenija Čarnojevića",
      "Bulevar Kr. Aleksandra",
      "Bulevar Nemanjića",
      "Bulevar Oslobođenja",
      "Bulevar Patrijarha Pavla",
      "Bulevar Vojvode Mišića",
      "Bulevar kralja Aleksandra",
      "Bulevar maršala Tolbuhina",
      "Bulevar oslobođenja",
      "Bulevar zona",
      "Cara Dusana",
      "Cara Dušana",
      "Cara Lazara",
      "Cara Lazara 87C odskora Branislava Nušića 18",
      "Centar",
      "Centar (uži)",
      "Centar 1",
      "Centar 3",
      "Centar preko Lepenice",
      "Cerak",
      "Cerak vinogradi",
      "Crnogorska",
      "Crvena Zvezda",
      "Crveni Krst",
      "Crveni krst",
      "Crveni pevac",
      "Cvetanova ćuprija",
      "Cvetkova pijaca",
      "Cvetni trg",
      "Cvijićeva",
      "DUNAVSKA",
      "Dalmatinska",
      "Dedinje (25. maj)",
      "Dedinje (Beli dvor)",
      "Dedinje (RTV Pink)",
      "Deli Radivoja",
      "Delijski vis",
      "Denkova bašta",
      "Detelinara",
      "Detelinara nova",
      "Dimitrija Tucovića",
      "Divcibare",
      "Divčibare",
      "Divčibarska",
      "Dobanovci",
      "Donji Dorćol",
      "Dr.Dimitrija Jovčića",
      "Dragoslava Srejovića",
      "Dubočica",
      "Dubrava",
      "Dudovi",
      "Dukley",
      "Dunavska",
      "Dunavski kej",
      "Durlan",
      "Duvanište",
      "Dušanovac",
      "Duška Radovića",
      "Erdoglija",
      "Erska",
      "Farmaceutski fakultet",
      "Fešter",
      "Filipa Visnjica",
      "Filipa Višnjića",
      "Filmski grad",
      "Fočanska1",
      "Fruškogorski put",
      "Futog",
      "Futoska",
      "Futoška pijaca",
      "Futoški put",
      "Gabrovačka reka",
      "Galenika",
      "Gavrila Principa",
      "Godjevacka",
      "Golf naselje",
      "Golija",
      "Golubinci",
      "Gornja Kamenica",
      "Gornjačka",
      "Gornji Dorćol",
      "Gornji grad Margita",
      "Gornjomatejevacka",
      "Gočki put",
      "Grada Sirena",
      "Gradska bolnica",
      "Grbavica",
      "Grocka (centar)",
      "Gundulićev venac",
      "HILANDARSKA",
      "Hadžipopovac",
      "Hala Pionir",
      "Institut",
      "Institut za majku i dete",
      "Ivana Milutinovića",
      "Ive Andića",
      "Ive Andrića",
      "Ive Lole Ribara",
      "Jablanova",
      "Jadranski put",
      "Jagodin mala",
      "Jajinci",
      "Jakovo",
      "Jelena Anžujska",
      "Jelene Lozanić",
      "Jezero",
      "Jodna banja",
      "Jovana Cvijića",
      "Jovana Mikića Spartak",
      "Jovana Ristica",
      "Jovanke Jeftanović",
      "Jove Ilića",
      "Jugovićevo",
      "Julino brdo",
      "Jurija Gagarina",
      "Južni bulevar",
      "KNEZA MILOSA",
      "KOPAONIK",
      "Kajsijar",
      "Kalač brdo",
      "Kalemegdan",
      "Kalenić pijaca",
      "Kaluđerica",
      "Kamalj",
      "Kamenjar",
      "Kanarevo brdo",
      "Karaburma",
      "Karagača",
      "Karaman",
      "Karaula",
      "Karađorđeva",
      "Karlovački drum",
      "Kej Radoja Dakića",
      "Kertvaroš",
      "Kikindska",
      "Kiridžijska",
      "Kičevo",
      "Klinički centar",
      "Klisa",
      "Klisura",
      "Kluz",
      "Knez Mihailova ( centar )",
      "Kneza Mihajla Obrenovića",
      "Kneza Miloša",
      "Kneza Miloša ( centar )",
      "Kneževac",
      "Knjaza Miloša",
      "Knjazevacka",
      "Kod Uspinjače",
      "Komren",
      "Konaci",
      "Konjarnik",
      "Kopaonik",
      "Kopitareva gradina",
      "Kosančićev venac",
      "Kosmaj",
      "Koste Jovanovića",
      "Kotež",
      "Kotež 1",
      "Kotež 2",
      "Kozačinskog",
      "Košutnjak",
      "Kragujevačka",
      "Kralja Milana IV",
      "Kralja Milutina",
      "Kralja Petra Prvog",
      "Kraljevi Čardaci",
      "Kraljevića Marka",
      "Krcmarska 14",
      "Krnjača",
      "Kudoš",
      "Kumodraž I",
      "Kumodraž II",
      "Labudovo brdo",
      "Lagator",
      "Ledine",
      "Lekino brdo",
      "Levač",
      "Leštane",
      "Liman 1",
      "Liman 2",
      "Liman 3",
      "Liman 4",
      "Lion",
      "Lipov gaj",
      "Lipov lad",
      "Lipova",
      "Lustica Bay - Marina naselje",
      "Luštica",
      "Luštica bay",
      "Luštica bay, Centrale",
      "MIODRAGA PETROVICA CKALJE",
      "MIodraga Petrovića Čkalje",
      "Maksima Gorkog",
      "Mala vaga",
      "Mali mokri lug",
      "Mandic Sokak 7",
      "Manjež",
      "Marger",
      "Marije Mate Magazinović",
      "Markovo polje",
      "Markuševina",
      "Marsala Tita",
      "Maršala Tita",
      "Maršala Tita 146",
      "Maršla Tita",
      "Mažina",
      "Medak padina",
      "Medaković I",
      "Medaković II",
      "Medaković III",
      "Mediana",
      "Medijana",
      "Mediteranska",
      "Mediteranska ulica, centar",
      "Mesna zajednica V",
      "Meteorološka",
      "Miladina Pećinara",
      "Milana Tepića",
      "Mileve Marić Ajnštajn",
      "Milice Stojadinovic 15",
      "Milice Stojadinović",
      "Milice Stojadinović Srpkinje",
      "Miljakovac I",
      "Miljakovac II",
      "Miljakovac III",
      "Miloja Čiplića",
      "Miodraga Vlajića Šuke",
      "Mirijevo I",
      "Mirijevo II",
      "Mirijevo III",
      "Mirijevo IV",
      "Mišeluk",
      "Mladost",
      "Moravska",
      "Mramorska",
      "Negotinska",
      "Neimar",
      "Nemanjina",
      "Nemanjina 7",
      "Nepoznato",
      "Nika Anđusa",
      "Niška Banja",
      "Nova Pazova",
      "Nova Selenča",
      "Nova misa",
      "Nova misa vinogradi",
      "Nova železnička kolonija",
      "Novi Banovci",
      "Novi Beograd",
      "Novi Beograd Blok 1 (Fontana)",
      "Novi Beograd Blok 11 (Hotel Jugoslavija)",
      "Novi Beograd Blok 11a (Opština NBG)",
      "Novi Beograd Blok 11b",
      "Novi Beograd Blok 11c (Stari Merkator)",
      "Novi Beograd Blok 12 (YUBC)",
      "Novi Beograd Blok 19 (Sava Centar)",
      "Novi Beograd Blok 19a",
      "Novi Beograd Blok 2",
      "Novi Beograd Blok 21 (10. Gimnazija)",
      "Novi Beograd Blok 22",
      "Novi Beograd Blok 23",
      "Novi Beograd Blok 24 (Super Vero)",
      "Novi Beograd Blok 25 (Arena)",
      "Novi Beograd Blok 28 (Potkovica)",
      "Novi Beograd Blok 29",
      "Novi Beograd Blok 3",
      "Novi Beograd Blok 30 (B92)",
      "Novi Beograd Blok 31 (Merkator)",
      "Novi Beograd Blok 32 (Crkva sv. Dimitrija)",
      "Novi Beograd Blok 33 (Genex kula)",
      "Novi Beograd Blok 34 (Studentski grad)",
      "Novi Beograd Blok 37",
      "Novi Beograd Blok 38 (OŠ Ratko Mitrović)",
      "Novi Beograd Blok 4 (Politehnička akademija)",
      "Novi Beograd Blok 44 (Piramida)",
      "Novi Beograd Blok 45 (TC Enjub)",
      "Novi Beograd Blok 49",
      "Novi Beograd Blok 5",
      "Novi Beograd Blok 58",
      "Novi Beograd Blok 60",
      "Novi Beograd Blok 60 (Airport City)",
      "Novi Beograd Blok 61",
      "Novi Beograd Blok 62",
      "Novi Beograd Blok 63",
      "Novi Beograd Blok 64",
      "Novi Beograd Blok 65",
      "Novi Beograd Blok 66 (Tramvajska štala)",
      "Novi Beograd Blok 67 (Belvil)",
      "Novi Beograd Blok 67a",
      "Novi Beograd Blok 68",
      "Novi Beograd Blok 7 (Paviljoni)",
      "Novi Beograd Blok 70 (Kineski TC)",
      "Novi Beograd Blok 70a",
      "Novi Beograd Blok 71",
      "Novi Beograd Blok 72",
      "Novi Beograd Blok 7a (Paviljoni)",
      "Novi Beograd Blok 8 (Paviljoni)",
      "Novi Beograd Blok 8a",
      "Novi Beograd Blok 9",
      "Novi Beograd Blok 9a (Dom Zdravlja)",
      "Novi Kopaonik",
      "Novi Majur",
      "Novi Vinodolski",
      "Novi majur",
      "Novo Naselje",
      "Novo groblje",
      "Novo naselje",
      "Novosadska",
      "Obilićev venac",
      "Obudojevica",
      "Olge Grbić",
      "Olge Jovičić",
      "Olimp",
      "Omladinskih Brigada",
      "Omladinskih brigada",
      "Oslobođenja",
      "Ostružnica",
      "Ovča",
      "Padinska skela",
      "Palata pravde",
      "Palilula",
      "Palilule",
      "Palilulska",
      "Palilulska pijaca",
      "Palisad",
      "Pantelej",
      "Paragovo",
      "Partizanov stadion",
      "Pasi poljana",
      "Patrijarha Pavla",
      "Pavla Vuisića",
      "Pašino brdo",
      "Pejton",
      "Pere Segedinca",
      "Petlovo brdo",
      "Petrovaradin",
      "Pirandelova",
      "Piskavac",
      "Pivara",
      "Plavi Horizonti",
      "Podbara",
      "Politika ( centar )",
      "Popova plaža",
      "Popovica",
      "Porto Montenegro",
      "Portonovi",
      "Poručnika Savičića i Radića",
      "Potoci",
      "Poštanska štedionica",
      "Pregrevica",
      "Preradovićeva",
      "Prijepolje (Centar)",
      "Profesorska kolonija",
      "Proleterska",
      "Prozivka",
      "Puckaroš",
      "Put Jovana Cvijica 20",
      "Put za koloniju, Ripanj",
      "Radijalac",
      "Radiofar",
      "Radnička",
      "Raj",
      "Rakovica",
      "Ratko Jović",
      "Repu",
      "Resnik",
      "Retenzija",
      "Ribljja pijaca",
      "Rojkovac",
      "Rose",
      "Rospi ćuprija",
      "Rotkvarija",
      "Rozino",
      "Rsavci",
      "Rudo",
      "Rujanska",
      "Rušanj",
      "Ruža Šulman",
      "Rvati",
      "SREBRNA PLANINA",
      "STEFANA PRVOVENCANOG",
      "SUNCANI BREG",
      "Sadovi",
      "Sajam",
      "Sajlovo",
      "Sajmište",
      "Salajka",
      "Sarajevska",
      "Sarina međa",
      "Satelit",
      "Sava mala",
      "Save Munćana",
      "Savski trg",
      "Savski venac",
      "Senica",
      "Senjak",
      "Severni bulevar",
      "Sime Miljuša",
      "Sindjelićeva 47",
      "Skadarlija",
      "Skojevsko naselje",
      "Slana bara",
      "Slatina",
      "Slavija",
      "Slavujev venac",
      "Sloboda",
      "Slobode",
      "Snežnik",
      "Socijalno",
      "Sodara",
      "Somborska",
      "Somborski bulevar",
      "Spens",
      "Sportska",
      "Sportska 39",
      "Sportska 39A",
      "Srebrno jezero",
      "Sremčica",
      "Stanoja Bunuševca",
      "Stanovo",
      "Stara Pazova",
      "Stari Banovci",
      "Stari Grad",
      "Stari Majur",
      "Stari majur",
      "Staro groblje",
      "Stefana Prvovencanog",
      "Stefana Prvovencanog 33",
      "Stefana Prvovenčanog",
      "Stefana Prvovenčanog 170",
      "Stefana Prvovenčanog 52",
      "Stefana prvovencanog",
      "Stepa Stepanović",
      "Stevana Mokranjca",
      "Stevana Prvovenčanog",
      "Stojana Vukosavljevića",
      "Stočnjak",
      "Strahinjića Bana",
      "Stražilovska",
      "Strelište 1",
      "Studentska",
      "Studentski Trg ( centar )",
      "Subotički bulevar",
      "Sulejiceva",
      "Sunčana padina",
      "Sunčani Breg",
      "Sunčani breg",
      "Surčin (centar)",
      "Svetog Dimitrija",
      "Svetog Save",
      "Svetog Save 1",
      "Svetogorska",
      "Svetozara Krstića",
      "Svetozara Markovića",
      "Svetozara Miletića",
      "Svetozara Miletića 44",
      "TANASKA RAJICA",
      "TRG POLITIKA",
      "Tabane",
      "Tatarsko brdo",
      "Tašmajdan",
      "Tehnički fakultet",
      "Telep",
      "Temerinski put",
      "Terazije",
      "Terazije ( centar )",
      "Tesla",
      "Tihomira Arsića",
      "Tivol",
      "Todora Mišića Španca",
      "Topla",
      "Topličin venac",
      "Topčider",
      "Tošin bunar",
      "Trandžament",
      "Tranšpedova",
      "Treska",
      "Trešnja",
      "Trg Republike ( centar )",
      "Trg mladenaca",
      "Trg slobode",
      "Trošarina",
      "Ujedinjene nacije",
      "Ul.2o.jula 1d",
      "Umina Voda",
      "Učiteljsko naselje",
      "Užička",
      "Vakuf",
      "Vardarska",
      "Vase Ostojića",
      "Vašarište",
      "Veliki mokri lug",
      "Veljko Vlahović",
      "Venac",
      "Veternik",
      "Veternička rampa",
      "Veterničko brdo",
      "Vidikovac",
      "Vidikovačka padina",
      "Vidikovački venac",
      "Vidovdansko naselje",
      "Vikend Naselje",
      "Vikend naselje",
      "Vinča",
      "Viogorska",
      "Višnjica",
      "Višnjička banja",
      "Vodice",
      "Vojlovica",
      "Vojvode Demira",
      "Vojvode Misica",
      "Vojvode Mišića",
      "Vojvode Putnika",
      "Vojvode Stepe",
      "Vojvode Tankosića",
      "Vojvode Vlahovića",
      "Voždovac",
      "Vranjevina",
      "Vranjevina - Čolovića brdo",
      "Vračar (Centar)",
      "Vračar (Hram)",
      "Vrežina",
      "Vršačka",
      "Vukov spomenik",
      "Zaovine",
      "Zebinovac",
      "Zelengorska",
      "Zeleni venac",
      "Zeleno Brdo",
      "Zemun (13. maj)",
      "Zemun (Bačka)",
      "Zemun (Cara Dušana)",
      "Zemun (Centar)",
      "Zemun (Donji grad)",
      "Zemun (Gardoš)",
      "Zemun (Gornji grad)",
      "Zemun (Kalvarija)",
      "Zemun (Kej)",
      "Zemun (Marije Bursać)",
      "Zemun (Meandri)",
      "Zemun (Nova Galenika)",
      "Zemun (Novi Grad)",
      "Zemun (Save Kovačevića)",
      "Zemun (Sutjeska)",
      "Zemun (Zemunske kapije)",
      "Zemun (Ćukovac)",
      "Zemun Polje",
      "Zira",
      "Zlatibor 1",
      "Zmaj Jove Jovanovića",
      "Zmaj Jovina",
      "Zova",
      "Zvezdara",
      "Zvezdarska Šuma",
      "Zvezdin stadion",
      "nemanjina",
      "svetozara markovića",
      "vatrogasna",
      "Ćaldov put",
      "Ćele kula",
      "Ćirpanova",
      "Čair",
      "Čajetina",
      "Čalije",
      "Čardak",
      "Časlava Veljića",
      "Čegarska",
      "Čigota",
      "Čolovića brdo",
      "Čubura",
      "Čukarica",
      "Čukarička padina",
      "Đačkog bataljona",
      "Đeram pijaca",
      "Đurkovac",
      "Šafarikova",
      "Šarengrad",
      "Širi centar",
      "Šulejićeva",
      "Šumice",
      "Žarka Zrenjanina",
      "Žarkovo",
      "Železnik",
      "Železnička",
      "Železnička stanica",
      "Ženeva (Devizno naselje)",
      "Žitni trg",
      "Živinarnik",
      "Гођевачка 36"
    ],
    "heating_types": [
      "Centralno",
      "Centralno, Etažno",
      "Centralno, Klima",
      "Centralno, Klima, Etažno",
      "Centralno, Klima, Podno, Kamin",
      "Centralno, Klima, Toplotna pumpa",
      "Centralno, Ostalo",
      "Centralno, Podno",
      "Centralno, TA peć",
      "Centralno, Toplotna pumpa",
      "Etažno",
      "Etažno, Centralno",
      "Etažno, Kamin",
      "Etažno, Klima",
      "Etažno, Klima, Podno",
      "Etažno, Ostalo",
      "Etažno, Podno",
      "Etažno, Podno, Toplotna pumpa",
      "Etažno, TA peć",
      "Etažno, Toplotna pumpa",
      "Kamin, Centralno",
      "Kamin, Etažno",
      "Kamin, Etažno, Klima",
      "Kamin, Klima",
      "Kamin, Klima, TA peć",
      "Klima",
      "Klima uređaj",
      "Klima, Centralno",
      "Klima, Centralno, Etažno",
      "Klima, Centralno, Ostalo",
      "Klima, Etažno",
      "Klima, Etažno, Centralno",
      "Klima, Etažno, Kamin",
      "Klima, Etažno, Ostalo",
      "Klima, Etažno, Podno",
      "Klima, Etažno, Podno, Centralno",
      "Klima, Etažno, Podno, Ostalo",
      "Klima, Etažno, Podno, TA peć",
      "Klima, Etažno, TA peć",
      "Klima, Kamin",
      "Klima, Ostalo",
      "Klima, Ostalo, Centralno",
      "Klima, Ostalo, Etažno",
      "Klima, Ostalo, Etažno, Podno",
      "Klima, Ostalo, Etažno, Podno, TA peć, Centralno",
      "Klima, Ostalo, Etažno, TA peć",
      "Klima, Ostalo, Kamin",
      "Klima, Ostalo, Podno",
      "Klima, Ostalo, Podno, Centralno",
      "Klima, Ostalo, Podno, Etažno",
      "Klima, Ostalo, TA peć",
      "Klima, Ostalo, TA peć, Centralno",
      "Klima, Ostalo, TA peć, Etažno",
      "Klima, Peć",
      "Klima, Podno",
      "Klima, Podno, Centralno",
      "Klima, Podno, Etažno",
      "Klima, Podno, Etažno, Centralno",
      "Klima, Podno, Ostalo",
      "Klima, TA peć",
      "Klima, TA peć, Etažno",
      "Klima, TA peć, Ostalo",
      "Klima, TA peć, Peć, Ostalo",
      "Klima, Toplotna pumpa",
      "Nepoznato",
      "Ostalo",
      "Ostalo, Centralno",
      "Ostalo, Etažno",
      "Ostalo, Etažno, TA peć",
      "Ostalo, Klima",
      "Ostalo, Podno",
      "Ostalo, TA peć",
      "Ostalo, TA peć, Klima",
      "Peć",
      "Peć, Klima, Podno",
      "Peć, TA peć",
      "Plinska peć, TA peć, Klima",
      "Podno",
      "Podno, Centralno",
      "Podno, Etažno",
      "Podno, Klima",
      "Podno, Ostalo",
      "Podno, Toplotna pumpa",
      "TA peć",
      "TA peć, Etažno",
      "TA peć, Klima",
      "TA peć, Klima, Etažno",
      "TA peć, Klima, Peć",
      "TA peć, Peć",
      "TA peć, Peć, Klima",
      "Toplotna pumpa",
      "Toplotna pumpa, Centralno",
      "Toplotna pumpa, Etažno",
      "Toplotna pumpa, Klima",
      "Toplotna pumpa, Podno",
      "Toplotna pumpa, Podno, Centralno",
      "Toplotna pumpa, Podno, Klima"
    ],
    "parking_options": [
      "Da",
      "Ne",
      "Nepoznato",
      "Spoljno parking mesto"
    ],
    "numeric_ranges": {
      "area_m2": {
        "min": 10.0,
        "median": 61.59,
        "max": 500.0
      },
      "rooms": {
        "min": 1.0,
        "median": 3.0,
        "max": 10.0
      },
      "year_built": {
        "min": 1900.0,
        "median": 2024.0,
        "max": 2028.0
      },
      "price_eur": {
        "min": 13500.0,
        "median": 160410.0,
        "max": 1000000.0
      }
    }
  },
  "cleaning_summary": {
    "raw_rows": 20584,
    "complete_key_rows": 20379,
    "duplicate_rows": 1357,
    "duplicate_groups": 498,
    "rows_removed_if_keeping_first": 859,
    "deduped_rows": 19725,
    "cleaned_rows": 18651,
    "rows_removed_total": 1933
  }
}